dvsd_cmp/run/results/synthesis/dvsd_cmp.v
//***************************************
// Vanshika Tanwar
//Verilog file: dvsd_cmp.v
//***************************************
module dvsd_cmp(
        //Input A        
A_in,                                                                                      
        //Input B
B_in,                                                      
        //When A is less than B, it is high
less_than,                                                                                                                                  
        //When A is equal to B, it is high
equal_to,
        //When A is greater than B, it is high
greater_than                                                                                                                                                                                                                                                      
);
        //Declaration of Input Ports.
    input [3:0] A_in;
    input [3:0] B_in;
        //Declarations of Output Ports.
    output less_than;
    output equal_to;
    output greater_than ;
        //Internal variables
        //reg declarations
     reg less_than;
     reg equal_to;
     reg greater_than;
        //When the inputs  A or B are changed then execute this block
    always @(A_in or B_in)
 begin
        //This block checks if A is Greater than B, Greater than is high
       if(A_in > B_in)                              
           begin                                        
                      less_than = 4'b0;      
                      equal_to =4'b0;
                      greater_than = 4'b1;    
           end
        //This block checks if A is equal to B, Equal to is high
       else if(A_in == B_in)                    
           begin                            
                      less_than = 4'b0;
                      equal_to = 4'b1;
                      greater_than = 4'b0;    
           end
        //Otherwise -This block checks for A less than B, Less than is high          
       else                                                  
           begin                                                  
                      less_than = 4'b1;
                      equal_to = 4'b0;
                      greater_than =4'b0;
        end
end
        //End of a module
endmodule

pre_layout/tb_dvsd_cmp.v
//***************************************
// Vanshika Tanwar
//Test Bench : tb_dvsd_cmp.v
//***************************************
`timescale 1ns / 1ps

module tb_dvsd_cmp;

    // Inputs
    reg [3:0] A_in;
    reg [3:0] B_in;

    // Outputs
    //Declarations of internal wire
    wire less_than;    
    wire equal_to;
    wire greater_than;

    // Instantiate the Unit Under Test (UUT)
    dvsd_cmp uut (
        .A_in(A_in),
        .B_in(B_in),
        .less_than(less_than),
        .equal_to(equal_to),
        .greater_than(greater_than)
    );

    initial begin
    //dump file
    $dumpfile("tb_dvsd_cmp.vcd");                                        
    $dumpvars(0,tb_dvsd_cmp);
    //Applying input values
        A_in = 1000;    
        B_in = 1001;    
        #100;

        A_in = 0010;    
        B_in = 1110;    
        #100;

        A_in = 1010;    
        B_in = 1010;      
        #100;

        A_in = 0111;      
        B_in = 0110;      
        #100;

        A_in = 1011;        
        B_in = 1111;          
        #100;

        A_in = 0011;        
        B_in = 1101;        
        #100;

        A_in = 1111;        
        B_in = 1111;          
        #100;

        A_in = 0001;          
        B_in = 1100;          
        #100;

        A_in = 0101;            
        B_in = 0100;                      
        #100;

        A_in = 0110;            
        B_in = 1001;                      
        #100;

        A_in = 0000;            
        B_in = 0000;                      
        #100;

        A_in = 1100;            
        B_in = 0011;                      
        #100;
        
        A_in = 1000;    
        B_in = 1001;    
        #100;

        A_in = 0010;    
        B_in = 1110;    
        #100;

        A_in = 1010;    
        B_in = 1010;      
        #100;

        A_in = 0111;      
        B_in = 0110;      
        #100;

        A_in = 1011;        
        B_in = 1111;          
        #100;

        A_in = 0011;        
        B_in = 1101;        
        #100;

        A_in = 1111;        
        B_in = 1111;          
        #100;

        A_in = 0001;          
        B_in = 1100;          
        #100;

        A_in = 0101;            
        B_in = 0100;                      
        #100;

        A_in = 0110;            
        B_in = 1001;                      
        #100;

        A_in = 0000;            
        B_in = 0000;                      
        #100;

        A_in = 1100;            
        B_in = 0011;                      
        #100;
        
        A_in = 1000;    
        B_in = 1001;    
        #100;

        A_in = 0010;    
        B_in = 1110;    
        #100;

        A_in = 1010;    
        B_in = 1010;      
        #100;

        A_in = 0111;      
        B_in = 0110;      
        #100;

        A_in = 1011;        
        B_in = 1111;          
        #100;

        A_in = 0011;        
        B_in = 1101;        
        #100;

        A_in = 1111;        
        B_in = 1111;          
        #100;

        A_in = 0001;          
        B_in = 1100;          
        #100;

        A_in = 0101;            
        B_in = 0100;                      
        #100;

        A_in = 0110;            
        B_in = 1001;                      
        #100;

        A_in = 0000;            
        B_in = 0000;                      
        #100;

        A_in = 1100;            
        B_in = 0011;                      
        #100;
        
        A_in = 1000;    
        B_in = 1001;    
        #100;

        A_in = 0010;    
        B_in = 1110;    
        #100;

        A_in = 1010;    
        B_in = 1010;      
        #100;

        A_in = 0111;      
        B_in = 0110;      
        #100;

        A_in = 1011;        
        B_in = 1111;          
        #100;

        A_in = 0011;        
        B_in = 1101;        
        #100;

        A_in = 1111;        
        B_in = 1111;          
        #100;

        A_in = 0001;          
        B_in = 1100;          
        #100;

        A_in = 0101;            
        B_in = 0100;                      
        #100;

        A_in = 0110;            
        B_in = 1001;                      
        #100;

        A_in = 0000;            
        B_in = 0000;                      
        #100;

        A_in = 1100;            
        B_in = 0011;                      
        #100;
        
        A_in = 1000;    
        B_in = 1001;    
        #100;

        A_in = 0010;    
        B_in = 1110;    
        #100;

        A_in = 1010;    
        B_in = 1010;      
        #100;

        A_in = 0111;      
        B_in = 0110;      
        #100;

        A_in = 1011;        
        B_in = 1111;          
        #100;

        A_in = 0011;        
        B_in = 1101;        
        #100;

        A_in = 1111;        
        B_in = 1111;          
        #100;

        A_in = 0001;          
        B_in = 1100;          
        #100;

        A_in = 0101;            
        B_in = 0100;                      
        #100;

        A_in = 0110;            
        B_in = 1001;                      
        #100;

        A_in = 0000;            
        B_in = 0000;                      
        #100;

        A_in = 1100;            
        B_in = 0011;                      
        #100;
        
        A_in = 1000;    
        B_in = 1001;    
        #100;

        A_in = 0010;    
        B_in = 1110;    
        #100;

        A_in = 1010;    
        B_in = 1010;      
        #100;

        A_in = 0111;      
        B_in = 0110;      
        #100;

        A_in = 1011;        
        B_in = 1111;          
        #100;

        A_in = 0011;        
        B_in = 1101;        
        #100;

        A_in = 1111;        
        B_in = 1111;          
        #100;

        A_in = 0001;          
        B_in = 1100;          
        #100;

        A_in = 0101;            
        B_in = 0100;                      
        #100;

        A_in = 0110;            
        B_in = 1001;                      
        #100;

        A_in = 0000;            
        B_in = 0000;                      
        #100;

        A_in = 1100;            
        B_in = 0011;                      
        #100;
    end
     
endmodule

pre_layout/tb_dvsd_cmp.vcd
$date
	Sat Aug 28 18:03:45 2021
$end
$version
	Icarus Verilog
$end
$timescale
	1ps
$end
$scope module tb_dvsd_cmp $end
$var wire 1 ! less_than $end
$var wire 1 " greater_than $end
$var wire 1 # equal_to $end
$var reg 4 $ A_in [3:0] $end
$var reg 4 % B_in [3:0] $end
$scope module uut $end
$var wire 4 & A_in [3:0] $end
$var wire 4 ' B_in [3:0] $end
$var reg 1 # equal_to $end
$var reg 1 " greater_than $end
$var reg 1 ! less_than $end
$upscope $end
$upscope $end
$enddefinitions $end
#0
$dumpvars
b1001 '
b1000 &
b1001 %
b1000 $
0#
0"
1!
$end
#100000
1"
0!
b110 %
b110 '
b1010 $
b1010 &
#200000
0"
1#
b10 %
b10 '
b10 $
b10 &
#300000
1"
0#
b1110 %
b1110 '
b1111 $
b1111 &
#400000
0"
1!
b111 %
b111 '
b11 $
b11 &
#500000
b1101 %
b1101 '
b1011 $
b1011 &
#600000
1#
0!
b111 %
b111 '
b111 $
b111 &
#700000
0#
1!
b1100 %
b1100 '
b1 $
b1 &
#800000
1"
0!
b100 %
b100 '
b101 $
b101 &
#900000
b1001 %
b1001 '
b1110 $
b1110 &
#1000000
0"
1#
b0 %
b0 '
b0 $
b0 &
#1100000
1"
0#
b1011 %
b1011 '
b1100 $
b1100 &
#1200000
0"
1!
b1001 %
b1001 '
b1000 $
b1000 &
#1300000
1"
0!
b110 %
b110 '
b1010 $
b1010 &
#1400000
0"
1#
b10 %
b10 '
b10 $
b10 &
#1500000
1"
0#
b1110 %
b1110 '
b1111 $
b1111 &
#1600000
0"
1!
b111 %
b111 '
b11 $
b11 &
#1700000
b1101 %
b1101 '
b1011 $
b1011 &
#1800000
1#
0!
b111 %
b111 '
b111 $
b111 &
#1900000
0#
1!
b1100 %
b1100 '
b1 $
b1 &
#2000000
1"
0!
b100 %
b100 '
b101 $
b101 &
#2100000
b1001 %
b1001 '
b1110 $
b1110 &
#2200000
0"
1#
b0 %
b0 '
b0 $
b0 &
#2300000
1"
0#
b1011 %
b1011 '
b1100 $
b1100 &
#2400000
0"
1!
b1001 %
b1001 '
b1000 $
b1000 &
#2500000
1"
0!
b110 %
b110 '
b1010 $
b1010 &
#2600000
0"
1#
b10 %
b10 '
b10 $
b10 &
#2700000
1"
0#
b1110 %
b1110 '
b1111 $
b1111 &
#2800000
0"
1!
b111 %
b111 '
b11 $
b11 &
#2900000
b1101 %
b1101 '
b1011 $
b1011 &
#3000000
1#
0!
b111 %
b111 '
b111 $
b111 &
#3100000
0#
1!
b1100 %
b1100 '
b1 $
b1 &
#3200000
1"
0!
b100 %
b100 '
b101 $
b101 &
#3300000
b1001 %
b1001 '
b1110 $
b1110 &
#3400000
0"
1#
b0 %
b0 '
b0 $
b0 &
#3500000
1"
0#
b1011 %
b1011 '
b1100 $
b1100 &
#3600000
0"
1!
b1001 %
b1001 '
b1000 $
b1000 &
#3700000
1"
0!
b110 %
b110 '
b1010 $
b1010 &
#3800000
0"
1#
b10 %
b10 '
b10 $
b10 &
#3900000
1"
0#
b1110 %
b1110 '
b1111 $
b1111 &
#4000000
0"
1!
b111 %
b111 '
b11 $
b11 &
#4100000
b1101 %
b1101 '
b1011 $
b1011 &
#4200000
1#
0!
b111 %
b111 '
b111 $
b111 &
#4300000
0#
1!
b1100 %
b1100 '
b1 $
b1 &
#4400000
1"
0!
b100 %
b100 '
b101 $
b101 &
#4500000
b1001 %
b1001 '
b1110 $
b1110 &
#4600000
0"
1#
b0 %
b0 '
b0 $
b0 &
#4700000
1"
0#
b1011 %
b1011 '
b1100 $
b1100 &
#4800000
0"
1!
b1001 %
b1001 '
b1000 $
b1000 &
#4900000
1"
0!
b110 %
b110 '
b1010 $
b1010 &
#5000000
0"
1#
b10 %
b10 '
b10 $
b10 &
#5100000
1"
0#
b1110 %
b1110 '
b1111 $
b1111 &
#5200000
0"
1!
b111 %
b111 '
b11 $
b11 &
#5300000
b1101 %
b1101 '
b1011 $
b1011 &
#5400000
1#
0!
b111 %
b111 '
b111 $
b111 &
#5500000
0#
1!
b1100 %
b1100 '
b1 $
b1 &
#5600000
1"
0!
b100 %
b100 '
b101 $
b101 &
#5700000
b1001 %
b1001 '
b1110 $
b1110 &
#5800000
0"
1#
b0 %
b0 '
b0 $
b0 &
#5900000
1"
0#
b1011 %
b1011 '
b1100 $
b1100 &
#6000000
0"
1!
b1001 %
b1001 '
b1000 $
b1000 &
#6100000
1"
0!
b110 %
b110 '
b1010 $
b1010 &
#6200000
0"
1#
b10 %
b10 '
b10 $
b10 &
#6300000
1"
0#
b1110 %
b1110 '
b1111 $
b1111 &
#6400000
0"
1!
b111 %
b111 '
b11 $
b11 &
#6500000
b1101 %
b1101 '
b1011 $
b1011 &
#6600000
1#
0!
b111 %
b111 '
b111 $
b111 &
#6700000
0#
1!
b1100 %
b1100 '
b1 $
b1 &
#6800000
1"
0!
b100 %
b100 '
b101 $
b101 &
#6900000
b1001 %
b1001 '
b1110 $
b1110 &
#7000000
0"
1#
b0 %
b0 '
b0 $
b0 &
#7100000
1"
0#
b1011 %
b1011 '
b1100 $
b1100 &
